ort/__init__.py
ort/generator.py
ort/parser.py
ort/value.py
ort_python-1.0.1.dist-info/licenses/LICENSE
ort_python-1.0.1.dist-info/METADATA
ort_python-1.0.1.dist-info/WHEEL
ort_python-1.0.1.dist-info/top_level.txt
ort_python-1.0.1.dist-info/RECORD
