Metadata-Version: 2.4
Name: ort-python
Version: 1.0.1
Summary: Object Record Table - a CSV like structured data format with native object and array support.
Author: BACKGWA
License: MIT
Project-URL: Homepage, https://github.com/BackGwa/ORT
Project-URL: Repository, https://github.com/BackGwa/ORT
Requires-Python: >=3.7
License-File: LICENSE
Dynamic: license-file
